combinatorapi/.deta/prog_info
combinatorapi/.deta/state
combinatorapi/__init__.py
combinatorapi/helper/__init__.py
combinatorapi/helper/article.py
combinatorapi/helper/schemas/article.py
combinatorapi/helper/web_scraper/combinator.py
combinatorapi/helper/web_scraper/web_scraper.py
combinatorapi/main.py
combinatorapi/requirements.txt
combinatorapi-0.1.0.dist-info/entry_points.txt
combinatorapi-0.1.0.dist-info/WHEEL
combinatorapi-0.1.0.dist-info/METADATA
combinatorapi-0.1.0.dist-info/RECORD
