Metadata-Version: 2.1
Name: combinatorapi
Version: 0.1.0
Summary: 
Author: amarokkin
Author-email: jasminesingh.2011@gmail.com
Requires-Python: >=3.8,<4.0
Classifier: Programming Language :: Python :: 3
Classifier: Programming Language :: Python :: 3.10
Classifier: Programming Language :: Python :: 3.8
Classifier: Programming Language :: Python :: 3.9
Requires-Dist: bs4 (>=0.0.1,<0.0.2)
Requires-Dist: fastapi (>=0.75.1,<0.76.0)
Requires-Dist: requests (>=2.27.1,<3.0.0)
Requires-Dist: uvicorn (>=0.17.6,<0.18.0)
